tagging/base/__init__.py
tagging/base/base_tagging.py
tagging/base/parsetab.py
tagging/data_model/categories.csv
tagging/data_model/category_tags.txt
tagging/data_model/tag_refs.csv
tagging/data_model/tags.csv
tagging/data_model/units.txt
tagging/testing/__init__.py
tagging/testing/integration_test_interface.py
tagging/testing/test_base_tagging_unit.py
volttron_lib_tagging-0.1.1a4.dist-info/WHEEL
volttron_lib_tagging-0.1.1a4.dist-info/METADATA
volttron_lib_tagging-0.1.1a4.dist-info/RECORD
