Metadata-Version: 2.1
Name: volttron-lib-tagging
Version: 0.1.1a4
Summary: A base tagging agent api with extension points for using with the VOLTTRON platform. This base agent works with Haystack 3 tags
Home-page: https://github.com/eclipse-volttron/volttron-lib-tagging
License: Apache-2.0
Author: VOLTTRON Team
Author-email: volttron@pnnl.gov
Requires-Python: >=3.10,<4.0
Classifier: License :: OSI Approved :: Apache Software License
Classifier: Programming Language :: Python :: 3
Classifier: Programming Language :: Python :: 3.10
Classifier: Programming Language :: Python :: 3.11
Requires-Dist: ply (>=3.11,<4.0)
Requires-Dist: volttron (>=10.0.3a9,<11.0)
Project-URL: Repository, https://github.com/eclipse-volttron/volttron-lib-tagging
